LICENSE
MANIFEST.in
README.rst
VERSION
requirements.txt
setup.cfg
setup.py
helloworld/__init__.py
helloworld/classifiers.py
helloworld/featurizers.py
helloworld/generate_data.py
ycml/__init__.py
ycml.egg-info/PKG-INFO
ycml.egg-info/SOURCES.txt
ycml.egg-info/dependency_links.txt
ycml.egg-info/not-zip-safe
ycml.egg-info/requires.txt
ycml.egg-info/top_level.txt
ycml/classifiers/__init__.py
ycml/classifiers/base.py
ycml/classifiers/feature_selector.py
ycml/classifiers/gridsearch.py
ycml/classifiers/labels.py
ycml/classifiers/neural_networks.py
ycml/classifiers/thresholds.py
ycml/featclass/__init__.py
ycml/featclass/base.py
ycml/featclass/thresholds.py
ycml/featurizers/__init__.py
ycml/featurizers/base.py
ycml/http_daemon/__init__.py
ycml/http_daemon/__main__.py
ycml/http_daemon/decorators.py
ycml/scripts/__init__.py
ycml/scripts/evaluate.py
ycml/scripts/featurize.py
ycml/scripts/generate_key.py
ycml/scripts/partition_instances.py
ycml/scripts/partition_lines.py
ycml/scripts/predict.py
ycml/scripts/track_memory.py
ycml/scripts/train.py
ycml/transformers/__init__.py
ycml/transformers/base.py
ycml/transformers/misc.py
ycml/transformers/nlp.py
ycml/transformers/sequences.py
ycml/transformers/text.py
ycml/transformers/union.py
ycml/utils/__init__.py
ycml/utils/analysis.py
ycml/utils/cpus.py
ycml/utils/importing.py
ycml/utils/instances.py
ycml/utils/iterutils.py
ycml/utils/settings.py
ycml/utils/timer.py
ycml/utils/uriutils.py