Metadata-Version: 1.1
Name: ycml
Version: 0.1.12
Summary: yc's collection of convenience code for developing ML applications.
Home-page: http://github.com/skylander86/ycml
Author: yc sim
Author-email: hello@yanchuan.sg
License: Apache Software License 2.0
Keywords: machine learning,ml,natural language processing,nlp,utilities
Platform: UNKNOWN
Classifier: Development Status :: 2 - Pre-Alpha
Classifier: License :: OSI Approved :: Apache Software License
Classifier: Programming Language :: Python :: 3 :: Only
Classifier: Natural Language :: English
Classifier: Topic :: Scientific/Engineering :: Artificial Intelligence
Classifier: Topic :: Software Development :: Libraries
Classifier: Topic :: Utilities
Classifier: Operating System :: POSIX
